tapir_py/__init__.py
tapir_py/core.py
tapir_py/parts.py
tapir_py/tapir_py.py
tapir_py/utility.py
tapir_py-1.0.0.dist-info/LICENSE
tapir_py-1.0.0.dist-info/METADATA
tapir_py-1.0.0.dist-info/WHEEL
tapir_py-1.0.0.dist-info/top_level.txt
tapir_py-1.0.0.dist-info/RECORD
