Metadata-Version: 2.1
Name: tapir-py
Version: 1.0.0
Summary: A Python package to use the JSON API from ArchiCAD.
Home-page: https://github.com/ENZYME-APD/tapir-archicad-automation
Author: EnzymeAPD
Author-email: kaushiklsk96+tapir.py@gmail.com
Project-URL: Bug Tracker, https://github.com/ENZYME-APD/tapir-archicad-automation/issues
Classifier: Programming Language :: Python :: 2
Classifier: Programming Language :: Python :: 3
Classifier: Programming Language :: Python :: Implementation :: IronPython
Classifier: License :: OSI Approved :: GNU Affero General Public License v3 or later (AGPLv3+)
Requires-Python: >=2.7
License-File: LICENSE
